ext/models.cpp
ext/_bnm_linked.o
ext/models.cu.mako
ext/_bnm.o
ext/core.cpp
ext/models.cpp.mako
ext/bnm.cu
ext/fc.cu
ext/utils.cpp
ext/utils.cu
ext/libbnm.a
ext/bnm.cpp
ext/fc.cpp
ext/models.cu
ext/_bnm.cu
ext/models/bw.cpp
ext/models/rww.cpp
ext/models/bw.cu
ext/models/wc.cpp
ext/models/model.cu.mako
ext/models/kuramoto.cu
ext/models/rwwex.cpp
ext/models/rwwex.cu
ext/models/model.cpp.mako
ext/models/jr.cpp
ext/models/base.cpp
ext/models/kuramoto.cpp
ext/models/rww_fic.cpp
ext/models/jr.cu
ext/models/wc.cu
ext/models/rww.cu
cubnm.libs/libgomp-a34b3233.so.1.0.0
cubnm/_core.py
cubnm/__init__.py
cubnm/_setup_opts.py
cubnm/cli_parser.py
cubnm/utils.py
cubnm/cli.py
cubnm/datasets.py
cubnm/optimize.py
cubnm/_version.py
cubnm/core.cpython-39-x86_64-linux-gnu.so
cubnm/data/hcp/fcd/group-test303/REST/ctx_parc-schaefer-100_exc-inter_window-30_step-5_desc-fcdtril.npz
cubnm/data/hcp/fcd/group-test303/REST/ctx_parc-schaefer-100_window-30_step-5_desc-fcdtril.npz
cubnm/data/hcp/fcd/group-train706/REST/ctx_parc-schaefer-100_exc-inter_window-30_step-5_desc-fcdtril.npz
cubnm/data/hcp/fcd/group-train706/REST/ctx_parc-schaefer-100_window-30_step-5_desc-fcdtril.npz
cubnm/data/hcp/bold/100307/REST2_LR/ctx_parc-schaefer-100_desc-bold.npz
cubnm/data/hcp/bold/100307/REST1_LR/ctx_parc-schaefer-100_desc-bold.npz
cubnm/data/hcp/bold/100206/REST2_LR/ctx_parc-schaefer-100_desc-bold.npz
cubnm/data/hcp/bold/100206/REST1_LR/ctx_parc-schaefer-100_desc-bold.npz
cubnm/data/hcp/fc/group-test303/REST/ctx_parc-schaefer-100_desc-fc.npz
cubnm/data/hcp/fc/group-test303/REST/ctx_parc-schaefer-100_exc-inter_desc-fc.npz
cubnm/data/hcp/fc/group-train706/REST/ctx_parc-schaefer-100_desc-fc.npz
cubnm/data/hcp/fc/group-train706/REST/ctx_parc-schaefer-100_exc-inter_desc-fc.npz
cubnm/data/hcp/sc/group-test303/ctx_parc-schaefer-100_desc-length.npz
cubnm/data/hcp/sc/group-test303/ctx_parc-schaefer-100_desc-strength.npz
cubnm-0.1.0.dist-info/WHEEL
cubnm-0.1.0.dist-info/top_level.txt
cubnm-0.1.0.dist-info/RECORD
cubnm-0.1.0.dist-info/METADATA
cubnm-0.1.0.dist-info/entry_points.txt
cubnm-0.1.0.dist-info/licenses/LICENSE
