Metadata-Version: 2.4
Name: cubnm
Version: 0.1.0
Summary: A toolbox for brain network modeling on GPUs 
Author-email: Amin Saberi <amnsbr@gmail.com>
License: BSD 3-Clause License
Classifier: Development Status :: 3 - Alpha
Classifier: Intended Audience :: Science/Research
Classifier: Intended Audience :: Developers
Classifier: Programming Language :: C
Classifier: Programming Language :: C++
Classifier: Programming Language :: Python
Classifier: Programming Language :: Python :: 3
Classifier: Programming Language :: Python :: 3 :: Only
Classifier: Operating System :: Unix
Classifier: Environment :: GPU :: NVIDIA CUDA
Classifier: Topic :: Scientific/Engineering
Requires-Python: >=3.7
License-File: LICENSE
Requires-Dist: numpy<2,>=1.20
Requires-Dist: scipy
Requires-Dist: pandas
Requires-Dist: pymoo==0.6
Requires-Dist: tabulate
Requires-Dist: matplotlib
Requires-Dist: seaborn
Provides-Extra: cu11
Requires-Dist: cupy-cuda11x; extra == "cu11"
Requires-Dist: numba-cuda[cu11]; extra == "cu11"
Requires-Dist: nvidia-cublas-cu11; extra == "cu11"
Provides-Extra: cu12
Requires-Dist: cupy-cuda12x; extra == "cu12"
Requires-Dist: numba-cuda[cu12]; extra == "cu12"
Requires-Dist: nvidia-cublas-cu12; extra == "cu12"
Provides-Extra: cu13
Requires-Dist: cupy-cuda13x; extra == "cu13"
Requires-Dist: numba-cuda[cu13]; extra == "cu13"
Requires-Dist: nvidia-cublas; extra == "cu13"
Dynamic: license-file
